{
  "book": 45,
  "chapter": 12,
  "sections": [
    {
      "type": "heading",
      "heading": "基督裏的新生活"
    },
    {
      "type": "paragraph",
      "contents": [
        {
          "verseNum": 1,
          "hasVerseLabel": true,
          "verseText": "所以，弟兄姊妹，我凭上帝的怜悯劝你们献上自己的身体，作圣洁、蒙上帝悦纳的活祭。你们理当这样事奉。 "
        },
        {
          "verseNum": 2,
          "hasVerseLabel": true,
          "verseText": "你们不可追随世界的潮流，要随着思想的不断更新而改变，这样就能明辨上帝的旨意，知道什么是良善、纯全、蒙祂悦纳的。 "
        }
      ]
    },
    {
      "type": "paragraph",
      "contents": [
        {
          "verseNum": 2,
          "hasVerseLabel": false,
          "verseText": " "
        },
        {
          "verseNum": 3,
          "hasVerseLabel": true,
          "verseText": "我凭上帝赐给我的恩典劝告各位，不要自视过高，要照着上帝赐给各人的信心中肯地看待自己。 "
        },
        {
          "verseNum": 4,
          "hasVerseLabel": true,
          "verseText": "就像我们身体的各部分有不同的功能， "
        },
        {
          "verseNum": 5,
          "hasVerseLabel": true,
          "verseText": "我们众人在基督里组成一个身体，彼此联结，息息相关。 "
        },
        {
          "verseNum": 6,
          "hasVerseLabel": true,
          "verseText": "我们照所得的恩典各有不同的恩赐。说预言的，要按着信心的程度说预言； "
        },
        {
          "verseNum": 7,
          "hasVerseLabel": true,
          "verseText": "服侍的，要忠心服侍；教导的，要专一教导； "
        },
        {
          "verseNum": 8,
          "hasVerseLabel": true,
          "verseText": "劝勉的，要诚心劝勉；施舍的，要慷慨施舍；治理的，要殷勤治理；怜悯的，要甘心怜悯。 "
        }
      ]
    },
    {
      "type": "heading",
      "heading": "基督徒的生活守則"
    },
    {
      "type": "paragraph",
      "contents": [
        {
          "verseNum": 8,
          "hasVerseLabel": false,
          "verseText": " "
        },
        {
          "verseNum": 9,
          "hasVerseLabel": true,
          "verseText": "不可虚情假意地爱人。要疾恶如仇，一心向善。 "
        },
        {
          "verseNum": 10,
          "hasVerseLabel": true,
          "verseText": "要彼此相爱如同手足，互相尊重，彼此谦让。 "
        },
        {
          "verseNum": 11,
          "hasVerseLabel": true,
          "verseText": "要殷勤，不可懒惰，要常常火热地事奉主。 "
        },
        {
          "verseNum": 12,
          "hasVerseLabel": true,
          "verseText": "盼望中要有喜乐，患难中要坚忍，祷告要恒切。 "
        },
        {
          "verseNum": 13,
          "hasVerseLabel": true,
          "verseText": "信徒有缺乏，要慷慨帮助；客人来访，要热诚款待。 "
        },
        {
          "verseNum": 14,
          "hasVerseLabel": true,
          "verseText": "迫害你们的，要为他们祝福；要祝福，不可咒诅。 "
        },
        {
          "verseNum": 15,
          "hasVerseLabel": true,
          "verseText": "要与喜乐的人同乐，与哀哭的人同哭。 "
        },
        {
          "verseNum": 16,
          "hasVerseLabel": true,
          "verseText": "要彼此和睦，不可心高气傲，反要俯就卑微的人，不可自以为聪明。 "
        },
        {
          "verseNum": 17,
          "hasVerseLabel": true,
          "verseText": "不要以恶报恶。要尊重别人，众人都认为好的事，应该竭力去做。 "
        },
        {
          "verseNum": 18,
          "hasVerseLabel": true,
          "verseText": "如果可能，总要尽力与人和睦相处。 "
        },
        {
          "verseNum": 19,
          "hasVerseLabel": true,
          "verseText": "亲爱的弟兄姊妹，不要私自报复，要让上帝来审判，因为圣经上说： “主说，‘申冤在我，我必报应。’” "
        },
        {
          "verseNum": 20,
          "hasVerseLabel": true,
          "verseText": "所以， “你的仇敌若饿了，就给他吃的； 若渴了，就给他喝的； 你这样做是把炭火堆在他头上。” "
        },
        {
          "verseNum": 21,
          "hasVerseLabel": true,
          "verseText": "你不可被恶所胜，反要以善胜恶。 "
        }
      ]
    }
  ]
}