{"zec.11.9":{"versions":{"nasb":{"text":"Then I said, “I will not pasture you. What is to die, let it die, and what is to be annihilated, let it be annihilated; and let those who are left eat one another’s flesh.”"},"esv":{"text":"So I said, “I will not be your shepherd. What is to die, let it die. What is to be destroyed, let it be destroyed. And let those who are left devour the flesh of one another.”"},"cnv":{"text":"我就說：“我不再牧養你們了；那將要死的，讓他死吧！那將要被除滅的，讓他被除滅吧；那些餘剩的，讓他們彼此吞食對方的肉吧！”"},"ccb":{"text":"于是我说：“我不再牧养你们了。要死的就死吧，要灭亡的就灭亡吧，让剩下的互相吞吃吧。”"}}}}