{"isa.65.9":{"versions":{"nasb":{"text":"I will bring forth offspring from Jacob, And an heir of My mountains from Judah; Even My chosen ones shall inherit it, And My servants will dwell there."},"esv":{"text":"I will bring forth offspring from Jacob, and from Judah possessors of my mountains; my chosen shall possess it, and my servants shall dwell there."},"cnv":{"text":"我要從雅各中領出後裔， 從猶大中領出承受我眾山的； 我揀選的人必承受那地為業， 我的眾僕人必在那裡居住。"},"ccb":{"text":"“我必使雅各的后裔兴起， 使犹大人兴起， 继承我的群山。 我拣选的子民必拥有那片土地， 我的仆人必在那里安居。"},"csbs":{"text":"我必使后裔从雅各而出， 使我众山的继承人从犹大而来； 我的选民必拥有那地， 我的仆人们必居住在那里。"}}}}