{"num.1.24":{"versions":{"nasb":{"text":"Of the sons of Gad, their genealogical registration by their families, by their fathers’ households, according to the number of names, from twenty years old and upward, whoever was able to go out to war,"},"esv":{"text":"Of the people of Gad, their generations, by their clans, by their fathers’ houses, according to the number of the names, from twenty years old and upward, all who were able to go to war:"},"cnv":{"text":"迦得子孫的後代，照著他們的宗族、父家，根據人名數目，二十歲及以上，凡是能出去打仗的，都登記了；"}}}}