{"jdg.11.8":{"versions":{"nasb":{"text":"The elders of Gilead said to Jephthah, “For this reason we have now returned to you, that you may go with us and fight with the sons of Ammon and become head over all the inhabitants of Gilead.”"},"esv":{"text":"And the elders of Gilead said to Jephthah, “That is why we have turned to you now, that you may go with us and fight against the Ammonites and be our head over all the inhabitants of Gilead.”"},"cnv":{"text":"基列的長老對耶弗他說：“現在我們回到你這裡來，是要你與我們一同回去，與亞捫人爭戰，你要作我們基列所有居民的首領。”"},"ccb":{"text":"基列的众长老说：“现在我们是来请你跟我们一起回去抵抗亚扪人，你可以做所有基列人的首领。”"}}}}