{"lam.2.3":{"versions":{"nasb":{"text":"In fierce anger He has cut off All the strength of Israel; He has drawn back His right hand From before the enemy. And He has burned in Jacob like a flaming fire Consuming round about."},"esv":{"text":"He has cut down in fierce anger all the might of Israel; he has withdrawn from them his right hand in the face of the enemy; he has burned like a flaming fire in Jacob, consuming all around."},"cnv":{"text":"他在烈怒中砍斷以色列所有的角； 他從仇敵面前，收回自己的右手。 他像吞滅四周物件的火燄，在雅各中間焚燒。"},"ccb":{"text":"祂发烈怒毁灭以色列全军。 敌人袭来时，祂收回大能的手。 祂像烈焰一样吞噬雅各。"}}}}