{"2ki.11.4":{"versions":{"nasb":{"text":"Now in the seventh year Jehoiada sent and brought the captains of hundreds of the Carites and of the guard, and brought them to him in the house of the Lord. Then he made a covenant with them and put them under oath in the house of the Lord, and showed them the king’s son."},"esv":{"text":"But in the seventh year Jehoiada sent and brought the captains of the Carites and of the guards, and had them come to him in the house of the Lord. And he made a covenant with them and put them under oath in the house of the Lord, and he showed them the king’s son."},"cnv":{"text":"在第七年，耶何耶大派人把迦利人和衛兵的眾百夫長帶來，領他們進入耶和華的殿中，和他們立約，使他們在耶和華的殿裡起誓，然後把王子帶出來和他們見面。"},"ccb":{"text":"第七年，耶何耶大派人召迦利人和卫兵的百夫长们到耶和华的殿里，与他们立约，让他们在耶和华的殿里起誓，然后把约阿施王子带到他们面前。"}}}}