{"jer.38.20":{"versions":{"nasb":{"text":"But Jeremiah said, “They will not give you over. Please obey the Lord in what I am saying to you, that it may go well with you and you may live."},"esv":{"text":"Jeremiah said, “You shall not be given to them. Obey now the voice of the Lord in what I say to you, and it shall be well with you, and your life shall be spared."},"cnv":{"text":"耶利米說：“迦勒底人必不會把你交給他們。求你聽從我對你所說的耶和華的話；這樣，你就可以平安無事，你的性命也可以存活。"},"ccb":{"text":"耶利米说：“不会的。只要你听从耶和华吩咐我对你说的话，你就可以平安无事，保全性命。"}}}}