{
  "book": 58,
  "chapter": 8,
  "sections": [
    {
      "type": "heading",
      "heading": "更美之約的大祭司"
    },
    {
      "type": "paragraph",
      "contents": [
        {
          "verseNum": 1,
          "hasVerseLabel": true,
          "verseText": "以上所说的要点是：我们有这样的一位大祭司，已经坐在诸天之上至尊者的宝座右边， "
        },
        {
          "verseNum": 2,
          "hasVerseLabel": true,
          "verseText": "他是圣所和真会幕的服事者。这会幕是主所搭建的，不是人所搭建的。 "
        },
        {
          "verseNum": 3,
          "hasVerseLabel": true,
          "verseText": "每一位大祭司受委任，都是为了献上礼物和祭物；故此，这一位也必须有所献上。 "
        },
        {
          "verseNum": 4,
          "hasVerseLabel": true,
          "verseText": "既然如此，如果他在地上，就不会做祭司，因为地上已经有照着律法献祭物的祭司。 "
        },
        {
          "verseNum": 5,
          "hasVerseLabel": true,
          "verseText": "那些祭司所事奉的，是天上事物的模型和影子，就如摩西将要完成会幕的时候，得了神的指示，说：“你要注意，一切都要按照在山上指示你的样式去造。” "
        }
      ]
    },
    {
      "type": "paragraph",
      "contents": [
        {
          "verseNum": 5,
          "hasVerseLabel": false,
          "verseText": " "
        },
        {
          "verseNum": 6,
          "hasVerseLabel": true,
          "verseText": "但如今，耶稣得了更尊贵的服事工作，就像他也是更美好之约的中保那样；这约建立在各样更美好的应许之上。 "
        },
        {
          "verseNum": 7,
          "hasVerseLabel": true,
          "verseText": "原来，如果那第一个约是无可指责的，就没有寻求第二个约的必要了， "
        },
        {
          "verseNum": 8,
          "hasVerseLabel": true,
          "verseText": "因为神指责说： “看哪，时候就要到了！ 主说，我要与以色列家 和犹大家订立新约。 "
        }
      ]
    },
    {
      "type": "line-quote",
      "contents": [
        {
          "verseNum": 8,
          "hasVerseLabel": false,
          "verseText": "因为神指责说： “看哪，时候就要到了！ 主说，我要与以色列家 和犹大家订立新约。"
        }
      ]
    },
    {
      "type": "line-quote",
      "contents": [
        {
          "verseNum": 8,
          "hasVerseLabel": false,
          "verseText": "因为神指责说： “看哪，时候就要到了！ 主说，我要与以色列家 和犹大家订立新约。"
        }
      ]
    },
    {
      "type": "line-quote",
      "contents": [
        {
          "verseNum": 8,
          "hasVerseLabel": false,
          "verseText": " "
        },
        {
          "verseNum": 9,
          "hasVerseLabel": true,
          "verseText": "这约    不像从前我拉着他们祖先的手， 在领他们出埃及地的日子里 与他们所立的约。 因为他们没有持守我的约， 我就不理他们——这是主说的。 "
        }
      ]
    },
    {
      "type": "line-quote",
      "contents": [
        {
          "verseNum": 9,
          "hasVerseLabel": false,
          "verseText": "这约    不像从前我拉着他们祖先的手， 在领他们出埃及地的日子里 与他们所立的约。 因为他们没有持守我的约， 我就不理他们——这是主说的。"
        }
      ]
    },
    {
      "type": "line-quote",
      "contents": [
        {
          "verseNum": 9,
          "hasVerseLabel": false,
          "verseText": "这约    不像从前我拉着他们祖先的手， 在领他们出埃及地的日子里 与他们所立的约。 因为他们没有持守我的约， 我就不理他们——这是主说的。"
        }
      ]
    },
    {
      "type": "line-quote",
      "contents": [
        {
          "verseNum": 9,
          "hasVerseLabel": false,
          "verseText": "这约    不像从前我拉着他们祖先的手， 在领他们出埃及地的日子里 与他们所立的约。 因为他们没有持守我的约， 我就不理他们——这是主说的。"
        }
      ]
    },
    {
      "type": "line-quote",
      "contents": [
        {
          "verseNum": 9,
          "hasVerseLabel": false,
          "verseText": "这约    不像从前我拉着他们祖先的手， 在领他们出埃及地的日子里 与他们所立的约。 因为他们没有持守我的约， 我就不理他们——这是主说的。"
        }
      ]
    },
    {
      "type": "line-quote",
      "contents": [
        {
          "verseNum": 9,
          "hasVerseLabel": false,
          "verseText": "这约    不像从前我拉着他们祖先的手， 在领他们出埃及地的日子里 与他们所立的约。 因为他们没有持守我的约， 我就不理他们——这是主说的。"
        }
      ]
    },
    {
      "type": "line-quote",
      "contents": [
        {
          "verseNum": 9,
          "hasVerseLabel": false,
          "verseText": " "
        },
        {
          "verseNum": 10,
          "hasVerseLabel": true,
          "verseText": "主又说，在那些日子以后， 我要与以色列家订立这样的约： 我要把我的法则放在他们的意念中， 刻在他们的心上； 我将要做他们的神， 他们将要做我的子民。 "
        }
      ]
    },
    {
      "type": "line-quote",
      "contents": [
        {
          "verseNum": 10,
          "hasVerseLabel": false,
          "verseText": "主又说，在那些日子以后， 我要与以色列家订立这样的约： 我要把我的法则放在他们的意念中， 刻在他们的心上； 我将要做他们的神， 他们将要做我的子民。"
        }
      ]
    },
    {
      "type": "line-quote",
      "contents": [
        {
          "verseNum": 10,
          "hasVerseLabel": false,
          "verseText": "主又说，在那些日子以后， 我要与以色列家订立这样的约： 我要把我的法则放在他们的意念中， 刻在他们的心上； 我将要做他们的神， 他们将要做我的子民。"
        }
      ]
    },
    {
      "type": "line-quote",
      "contents": [
        {
          "verseNum": 10,
          "hasVerseLabel": false,
          "verseText": "主又说，在那些日子以后， 我要与以色列家订立这样的约： 我要把我的法则放在他们的意念中， 刻在他们的心上； 我将要做他们的神， 他们将要做我的子民。"
        }
      ]
    },
    {
      "type": "line-quote",
      "contents": [
        {
          "verseNum": 10,
          "hasVerseLabel": false,
          "verseText": "主又说，在那些日子以后， 我要与以色列家订立这样的约： 我要把我的法则放在他们的意念中， 刻在他们的心上； 我将要做他们的神， 他们将要做我的子民。"
        }
      ]
    },
    {
      "type": "line-quote",
      "contents": [
        {
          "verseNum": 10,
          "hasVerseLabel": false,
          "verseText": "主又说，在那些日子以后， 我要与以色列家订立这样的约： 我要把我的法则放在他们的意念中， 刻在他们的心上； 我将要做他们的神， 他们将要做我的子民。"
        }
      ]
    },
    {
      "type": "line-quote",
      "contents": [
        {
          "verseNum": 10,
          "hasVerseLabel": false,
          "verseText": "主又说，在那些日子以后， 我要与以色列家订立这样的约： 我要把我的法则放在他们的意念中， 刻在他们的心上； 我将要做他们的神， 他们将要做我的子民。"
        }
      ]
    },
    {
      "type": "line-quote",
      "contents": [
        {
          "verseNum": 10,
          "hasVerseLabel": false,
          "verseText": " "
        },
        {
          "verseNum": 11,
          "hasVerseLabel": true,
          "verseText": "他们绝不需要教导各自的同胞    、各自的兄弟，说： ‘你要认识主’—— 因为他们所有的人， 从卑微的到尊贵的， 都将认识我； "
        }
      ]
    },
    {
      "type": "line-quote",
      "contents": [
        {
          "verseNum": 11,
          "hasVerseLabel": false,
          "verseText": "他们绝不需要教导各自的同胞    、各自的兄弟，说： ‘你要认识主’—— 因为他们所有的人， 从卑微的到尊贵的， 都将认识我；"
        }
      ]
    },
    {
      "type": "line-quote",
      "contents": [
        {
          "verseNum": 11,
          "hasVerseLabel": false,
          "verseText": "他们绝不需要教导各自的同胞    、各自的兄弟，说： ‘你要认识主’—— 因为他们所有的人， 从卑微的到尊贵的， 都将认识我；"
        }
      ]
    },
    {
      "type": "line-quote",
      "contents": [
        {
          "verseNum": 11,
          "hasVerseLabel": false,
          "verseText": " "
        },
        {
          "verseNum": 12,
          "hasVerseLabel": true,
          "verseText": "又因为我要宽恕他们的不义， 绝不再想起他们的罪孽    。” "
        }
      ]
    },
    {
      "type": "line-quote",
      "contents": [
        {
          "verseNum": 12,
          "hasVerseLabel": false,
          "verseText": "又因为我要宽恕他们的不义， 绝不再想起他们的罪孽    。”"
        }
      ]
    },
    {
      "type": "paragraph-no-indent",
      "contents": [
        {
          "verseNum": 12,
          "hasVerseLabel": false,
          "verseText": " "
        },
        {
          "verseNum": 13,
          "hasVerseLabel": true,
          "verseText": "当神说到“新约”，就已经把第一个当做旧的；而那渐渐变旧、渐渐变老的，很快就要消逝了。 "
        }
      ]
    }
  ]
}